{
	"line_chart":"ચાર્ટ",
	"app_name":"કરન્સી કન્વર્ટર",
	"first_fragment_label":"પ્રથમ ટુકડો",
	"second_fragment_label":"બીજો ટુકડો",
	"next":"આગળ",
	"previous":"અગાઉના",
	"search":"શોધો",
	"copied_to_clipboard":"ક્લિપબોર્ડ પર ક Copપિ કરેલું",
	"hello_first_fragment":"હેલો પ્રથમ ટુકડો",
	"hello_second_fragment":"હેલો બીજો ટુકડો. દલીલ:% 1 $ s",
	"cpv_default_title":"રંગ પસંદ કરો",
	"cpv_presets":"પ્રીસેટ્સનો",
	"cpv_custom":"કસ્ટમ રંગ પસંદ કરો",
	"cpv_select":"પસંદ કરો",
	"cpv_transparency":"પારદર્શિતા",
	"widget_transparency":"વિજેટ પારદર્શિતા",
	"rate_the_app":"કૃપા કરીને અમારી એપ્લિકેશન રેટ કરો!",
	"rate_app_desc":"સ્ટાર્સ પર ટેપ કરો અને રેટ કરવા માટે &quot;ગૂગલ પ્લે સ્ટોર સાથે ખોલો&quot;",
	"not_now":"હમણાં નહીં",
	"updated_date":"અપડેટ:",
	"monetary_format":"નાણાકીય બંધારણ",
	"decimal_format":"દશાંશ ફોર્મેટ",
	"don_t_show":"બતાવશો નહીં",
	"support":"સહાય કરો",
	"terms":"શરતો",
	"privacy_policy":"ગોપનીયતા",
	"remove_ads":"જાહેરાત દૂર કરો",
	"sub_remove_ads":"નાના વાર્ષિક લવાજમ સાથે અમારા પ્રોજેક્ટને સપોર્ટ કરો",
	"language":"ભાષા",
	"color_selection":"રંગ પસંદગી",
	"select_the_gradient":"Theાળ પસંદ કરો",
	"unlocked":"અનલockedક કર્યું",
	"locked":"લ .ક થયેલ",
	"try_this_color":"આ રંગનો પ્રયાસ કરો",
	"sub_try_this_color":"તમે અનલlockક કરો તે પહેલાં પ્રયાસ કરો",
	"unlock":"અનલlockક કરો",
	"sub_unlock":"{item_price} માટે આ રંગને અનલlockક કરો",
	"theme":"થીમ",
	"light":"પ્રકાશ રંગ",
	"dark":"ડાર્ક કલર",
	"wedget_transparency":"વિજેટ પારદર્શિતા",
	"by_currency_wiki":"દ્વારા: કરન્સી.વીકી",
	"visual_size":"વિઝ્યુઅલ કદ",
	"small":"નાનું",
	"medium":"માધ્યમ",
	"large":"મોટું",
	"when_opening_app":"એપ્લિકેશન લોગો લ Laંચર",
	"display_multi_converter":"મલ્ટિ-કન્વર્ટર",
	"sub_multi_converter":"ડિફ defaultલ્ટ રૂપે મલ્ટિ-કન્વર્ટર ખોલશે. નોંધ: આ સુવિધા ફક્ત એપ્લિકેશન લોગો લ launંચર સાથે કાર્ય કરે છે.",
	"dislay":"બતાવો",
	"display_currency_code":"ચલણ કોડ બતાવો",
	"display_currency_symbol":"ચલણ પ્રતીક બતાવો",
	"display_currency_flag":"ચલણ ધ્વજ બતાવો",
	"date_format":"તારીખ ફોર્મેટ",
	"click_here":"⇒ અહીં ક્લિક કરો",
	"learn_how_to_nadd_widget":"વિજેટ કેવી રીતે ઉમેરવું તે શીખો",
	"selected":"પસંદ કરેલ",
	"currency_list":"વર્તમાન સૂચિ",
	"title_add_currency":"વર્તમાન ઉમેરો",
	"title_configure":"કન્ફિગર",
	"add_widget":"વિજેટ ઉમેરો",
	"convert_widget_single":"કન્વર્ટ - એકલ",
	"convert_widget_list":"કન્વર્ટ - સૂચિ",
	"title_select_base_currency":"બેઝ કરન્સી પસંદ કરો",
	"amount":"રકમ",
	"error_amount_empty":"કૃપા કરીને રકમ યોગ્ય રીતે દાખલ કરો",
	"internet_error":"કૃપા કરીને ઇન્ટરનેટથી કનેક્ટ થાઓ",
	"facebook_app_id":"248045086948204",
	"fb_login_protocol_scheme":"fb248045086948204",
	"tab_text_1":"Tab 1",
	"tab_text_2":"Tab 2",
	"title_activity_add_currency":"AddCurrencyActivity",
	"monetary_format_1":"1254.56",
	"monetary_format_2":"1.234,76",
	"monetary_format_3":"21 234.56",
	"monetary_format_4":"21 234,56",
	"decimal_format_1":".02",
	"decimal_format_2":".003",
	"decimal_format_3":".0004",
	"decimal_format_4":".00005",
	"decimal_format_5":".000006",
	"date_format_1":"mm/dd/yy",
	"date_format_2":"dd/mm/yy",
	"iso":"ગુજરાતી",
	"AED":"સંયુક્ત આરબ અમીરાત દિરહામ",
	"AFN":"અફઘાન અફઘાનિ",
	"ALL":"અલ્બેનિયન લેક",
	"AMD":"આર્મેનિયન ડ્રામ",
	"ANG":"નેધરલેન્ડ એન્ટિલિયન ગિલ્ડર",
	"AOA":"અંગોલાન ક્વાન્ઝા",
	"ARS":"આર્જેન્ટિના પેસો",
	"AUD":"Australianસ્ટ્રેલિયન ડlarલર",
	"AWG":"અરૂબન ફ્લોરિન",
	"AZN":"અઝરબૈજાની મનાત",
	"BAM":"બોસ્નિયા-હર્ઝેગોવિના કન્વર્ટિબલ માર્ક",
	"BBD":"બાર્બેડિયન ડlarલર",
	"BDT":"બાંગ્લાદેશી ટાકા",
	"BGN":"બલ્ગેરિયન લેવ",
	"BHD":"બહેરીની દીનાર",
	"BIF":"બરુન્ડિયન ફ્રાન્ક",
	"BMD":"બર્મુદાન ડોલર",
	"BND":"બ્રુનેઇ ડlarલર",
	"BOB":"બોલિવિયન બોલીવિયાનો",
	"BRL":"બ્રાઝિલિયન રીઅલ",
	"BSD":"બહામિયન ડlarલર",
	"BTC":"બિટકોઇન",
	"BTN":"ભૂટાનિઝ નગલ્ટ્રમ",
	"BWP":"બોત્સ્વાનાન પુલા",
	"BYN":"બેલારુશિયન રૂબલ",
	"BZD":"બેલીઝ ડlarલર",
	"CAD":"કેનેડિયન ડlarલર",
	"CDF":"કોંગોલીઝ ફ્રાન્ક",
	"CHF":"સ્વિસ ફ્રાન્ક",
	"CLF":"ખાતુંનું ચિલીયન યુનિટ (યુએફ)",
	"CLP":"ચિલીન પેસો",
	"CNY":"ચાઇનીઝ યુઆન",
	"COP":"કોલમ્બિયન પેસો",
	"CRC":"કોસ્ટા રિકન કોલોન",
	"CUC":"ક્યુબન કન્વર્ટિબલ પેસો",
	"CUP":"ક્યુબન પેસો",
	"CVE":"કેપ વર્ડિયન એસ્કોડો",
	"CZK":"ચેક રિપબ્લિક કોરુના",
	"DJF":"જીબ્યુટીઅન ફ્રાન્ક",
	"DKK":"ડેનિશ ક્રોન",
	"DOP":"ડોમિનિકન પેસો",
	"DZD":"અલ્જેરિયાના દીનાર",
	"EGP":"ઇજિપ્તની પાઉન્ડ",
	"ERN":"એરિટ્રિયન નાકફા",
	"ETB":"ઇથોપિયન બિર",
	"EUR":"યુરો",
	"FJD":"ફિજિયન ડlarલર",
	"FKP":"ફkકલેન્ડ આઇલેન્ડ પાઉન્ડ",
	"GBP":"બ્રિટીશ પાઉન્ડ સ્ટર્લિંગ",
	"GEL":"જ્યોર્જિયન લારી",
	"GGP":"ગાર્નસી પાઉન્ડ",
	"GHS":"ઘાનાની સેડી",
	"GIP":"જિબ્રાલ્ટર પાઉન્ડ",
	"GMD":"ગેમ્બિયન દલાસી",
	"GNF":"ગિનીન ફ્રાન્ક",
	"GTQ":"ગ્વાટેમાલાન ક્વેત્ઝાલ",
	"GYD":"ગિયાનાઇસ ડlarલર",
	"HKD":"હોંગકોંગ ડોલર",
	"HNL":"હોન્ડુરાન લેમ્પિરા",
	"HRK":"ક્રોએશિયન કુના",
	"HTG":"હૈતીયન ગૌર્ડે",
	"HUF":"હંગેરિયન ફોરિન્ટ",
	"IDR":"ઇન્ડોનેશિયન રૂપિયા",
	"ILS":"ઇઝરાઇલી ન્યૂ શેકેલ",
	"IMP":"માંક્સ પાઉન્ડ",
	"INR":"ભારતીય રૂપિયા",
	"IQD":"ઇરાકી દીનાર",
	"IRR":"ઈરાની રિયાલ",
	"ISK":"આઇસલેન્ડિક Króna",
	"JEP":"જર્સી પાઉન્ડ",
	"JMD":"જમૈકન ડlarલર",
	"JOD":"જોર્ડિયન દિનાર",
	"JPY":"જાપાનીઝ યેન",
	"KES":"કેન્યા શિલિંગ",
	"KGS":"કિર્ગીસ્તાની સોમ",
	"KHR":"કંબોડિયન રીએલ",
	"KMF":"કોમોરિયન ફ્રાન્ક",
	"KPW":"ઉત્તર કોરિયન જીત્યો",
	"KRW":"દક્ષિણ કોરિયન જીત્યો",
	"KWD":"કુવૈતી દિનાર",
	"KYD":"કેમેન આઇલેન્ડ્સ ડlarલર",
	"KZT":"કઝાકસ્તાની તેંગે",
	"LAK":"લાઓશિયન કીપ",
	"LBP":"લેબનીઝ પાઉન્ડ",
	"LKR":"શ્રીલંકન રૂપિયો",
	"LRD":"લાઇબેરિયન ડlarલર",
	"LSL":"લેસોથો લોટી",
	"LTL":"લિથુનિયન લિટાસ",
	"LVL":"લાતવિયન લેટ્સ",
	"LYD":"લિબિયન દિનાર",
	"MAD":"મોરોક્કન દિરહામ",
	"MDL":"મોલ્ડોવાન લિયુ",
	"MGA":"માલાગાસી એરિયરી",
	"MKD":"મેસેડોનિયન ડેનાર",
	"MMK":"મયન્મા ક્યાટ",
	"MNT":"મોંગોલિયન તુગરીક",
	"MOP":"મકાનીસ પટાકા",
	"MRO":"મૌરિટાનિયન ઓગ્યુઇઆ",
	"MUR":"મોરીશિયન રૂપિયો",
	"MVR":"માલદીવિયન રુફિયા",
	"MWK":"માલાવીયન ક્વાચા",
	"MXN":"મેક્સીકન પેસો",
	"MYR":"મલેશિયન રિંગગીટ",
	"MZN":"મોઝામ્બિકન મેટિકલ",
	"NAD":"નમિબિયન ડ Dolલર",
	"NGN":"નાઇજિરિયન નાયરા",
	"NIO":"નિકારાગુઆન કોર્ડોબા",
	"NOK":"નોર્વેજીયન ક્રોન",
	"NPR":"નેપાળી રૂપિયો",
	"NZD":"ન્યુ ઝિલેન્ડ ડlarલર",
	"OMR":"ઓમાની રિયાલ",
	"PAB":"પનામાનિયન બાલબોઆ",
	"PEN":"પેરુવિયન ન્યુવો સોલ",
	"PGK":"પપુઆ ન્યૂ ગિની કિના",
	"PHP":"ફિલિપિન પેસો",
	"PKR":"પાકિસ્તાની રૂપિયો",
	"PLN":"પોલિશ ઝ્લોટી",
	"PYG":"પેરાગ્વેયાન ગુરાની",
	"QAR":"કતારી રિયાલ",
	"RON":"રોમાનિયન લ્યુ",
	"RSD":"સર્બિયન દીનાર",
	"RUB":"રશિયન રૂબલ",
	"RWF":"રવાન્ડન ફ્રાન્ક",
	"SAR":"સાઉદી રિયાલ",
	"SBD":"સોલોમન આઇલેન્ડ્સ ડlarલર",
	"SCR":"સેશેલોઇસ રૂપિયા",
	"SDG":"સુદાનની પાઉન્ડ",
	"SEK":"સ્વીડિશ ક્રોના",
	"SGD":"સિંગાપોર ડlarલર",
	"SHP":"સેન્ટ હેલેના પાઉન્ડ",
	"SLL":"સીએરા લિયોનીન લિયોન",
	"SOS":"સોમાલી શિલિંગ",
	"SRD":"સુરીનામીઝ ડlarલર",
	"STD":"સાઓ ટોમે અને પ્રિન્સીપે ડોબ્રા",
	"SVC":"સાલ્વાડોરન કોલોન",
	"SYP":"સીરિયન પાઉન્ડ",
	"SZL":"સ્વાઝી લીલાંગેની",
	"THB":"થાઇ બાહત",
	"TJS":"તાજિકિસ્તાની સોમોની",
	"TMT":"તુર્કમેનિસ્તાની મનાટ",
	"TND":"ટ્યુનિશિયન દિનાર",
	"TOP":"ટોંગન પાંગા",
	"TRY":"ટર્કિશ લીરા",
	"TTD":"ત્રિનિદાદ અને ટોબેગો ડlarલર",
	"TWD":"ન્યુ તાઇવાન ડlarલર",
	"TZS":"તાંઝાનિયન શિલિંગ",
	"UAH":"યુક્રેનિયન રિવનિયા",
	"UGX":"યુગાન્ડા શિલિંગ",
	"USD":"યુનાઇટેડ સ્ટેટ્સ ડlarલર",
	"UYU":"ઉરુગ્વેન પેસો",
	"UZS":"ઉઝબેકિસ્તાન સોમ",
	"VES":"વેનેઝુએલાના બોલિવર ફુઅર્ટે",
	"VND":"વિયેતનામીસ ડોંગ",
	"VUV":"વનુઆતુ વતુ",
	"WST":"સમોન તાલા",
	"XAF":"સી.એફ.એ. ફ્રાન્ક બી.એ.સી.",
	"XAG":"ચાંદી (ટ્રોય ounceંસ)",
	"XAU":"સોનું (ટ્રોય ounceંસ)",
	"XCD":"પૂર્વ કેરેબિયન ડlarલર",
	"XDR":"વિશેષ ચિત્ર દોરવાનો અધિકાર",
	"XOF":"સીએફએ ફ્રાન્ક બીસીઇએઓ",
	"XPF":"સીએફપી ફ્રાન્ક",
	"YER":"યેમેની રિયલ",
	"ZAR":"દક્ષિણ આફ્રિકન રેન્ડ",
	"ZMK":"ઝામ્બિયન ક્વાચા (2013-પૂર્વે)",
	"ZMW":"ઝામ્બિયન ક્વાચા",
	"ZWL":"ઝિમ્બાબ્વે ડlarલર",
}
