{
	"line_chart":"चार्ट",
	"app_name":"मुद्रा परिवर्तक",
	"first_fragment_label":"पहला टुकड़ा",
	"second_fragment_label":"दूसरा टुकड़ा",
	"next":"अगला",
	"previous":"पहले का",
	"search":"खोज",
	"copied_to_clipboard":"क्लिपबोर्ड पर नकल",
	"hello_first_fragment":"हैलो पहला टुकड़ा",
	"hello_second_fragment":"नमस्ते दूसरा टुकड़ा। Arg:% 1 $ s",
	"cpv_default_title":"एक रंग का चयन करें",
	"cpv_presets":"प्रीसेट",
	"cpv_custom":"कस्टम रंग का चयन करें",
	"cpv_select":"चुनते हैं",
	"cpv_transparency":"पारदर्शिता",
	"widget_transparency":"विजेट पारदर्शिता",
	"rate_the_app":"हमारे app दर कृपया!",
	"rate_app_desc":"दर पर सितारों और &quot;Google Play Store के साथ खोलें&quot; पर टैप करें",
	"not_now":"अब मत",
	"updated_date":"अपडेट किया गया:",
	"monetary_format":"मौद्रिक स्वरूप",
	"decimal_format":"दशमलव स्वरूप",
	"don_t_show":"मत दिखाओ",
	"support":"हाथ बटाना",
	"terms":"मामले",
	"privacy_policy":"एकांत",
	"remove_ads":"विज्ञापन निकालें",
	"sub_remove_ads":"एक छोटी वार्षिक सदस्यता के साथ हमारी परियोजना का समर्थन करें",
	"language":"भाषा: हिन्दी",
	"color_selection":"रंग चयन",
	"select_the_gradient":"ढाल का चयन करें",
	"unlocked":"अनलॉक किया",
	"locked":"बंद",
	"try_this_color":"इस रंग की कोशिश करो",
	"sub_try_this_color":"अनलॉक करने से पहले प्रयास करें",
	"unlock":"अनलॉक",
	"sub_unlock":"इस रंग को {item_price} के लिए अनलॉक करें",
	"theme":"विषय",
	"light":"हल्का रंग",
	"dark":"गाढ़ा रंग",
	"wedget_transparency":"विजेट पारदर्शिता",
	"by_currency_wiki":"द्वारा: Currency.wiki",
	"visual_size":"दृश्य आकार",
	"small":"छोटा",
	"medium":"मध्यम",
	"large":"विशाल",
	"when_opening_app":"ऐप लोगो लॉन्चर",
	"display_multi_converter":"मल्टी-कन्वर्टर",
	"sub_multi_converter":"डिफ़ॉल्ट रूप से मल्टी-कन्वर्टर खोलेगा। नोट: यह सुविधा केवल ऐप लोगो लॉन्चर के साथ काम करती है।",
	"dislay":"प्रदर्शन",
	"display_currency_code":"मुद्रा कोड दिखाएं",
	"display_currency_symbol":"करेंसी सिंबल दिखाओ",
	"display_currency_flag":"मुद्रा ध्वज दिखाएं",
	"date_format":"डेटा प्रारूप",
	"click_here":"⇒ यहां क्लिक करें",
	"learn_how_to_nadd_widget":"विजेट जोड़ना सीखें",
	"selected":"चयनित",
	"currency_list":"सुरक्षा सूची",
	"title_add_currency":"ADD CURRENCY",
	"title_configure":"कॉन्फ़िगर",
	"add_widget":"विजेट जोड़ें",
	"convert_widget_single":"कन्वर्ट - सिंगल",
	"convert_widget_list":"कन्वर्ट - सूची",
	"title_select_base_currency":"बेस करेंसी का चयन करें",
	"amount":"रकम",
	"error_amount_empty":"कृपया राशि सही दर्ज करें",
	"internet_error":"कृपया इंटरनेट से कनेक्ट करें",
	"facebook_app_id":"248045086948204",
	"fb_login_protocol_scheme":"fb248045086948204",
	"tab_text_1":"Tab 1",
	"tab_text_2":"Tab 2",
	"title_activity_add_currency":"AddCurrencyActivity",
	"monetary_format_1":"1237.56",
	"monetary_format_2":"1.234,59",
	"monetary_format_3":"4 234.56",
	"monetary_format_4":"4 234,56",
	"decimal_format_1":".02",
	"decimal_format_2":".003",
	"decimal_format_3":".0004",
	"decimal_format_4":".00005",
	"decimal_format_5":".000006",
	"date_format_1":"mm/dd/yy",
	"date_format_2":"dd/mm/yy",
	"iso":"हिन्दी",
	"AED":"संयुक्त अरब अमीरात दिरहम",
	"AFN":"अफगान अफगानी",
	"ALL":"अल्बेनियाई लेक",
	"AMD":"आर्मेनियाई ड्राम",
	"ANG":"नीदरलैंड एंटिलियन गिल्डर",
	"AOA":"अंगोलन क्वांज़ा",
	"ARS":"अर्जेंटीना पेसो",
	"AUD":"ऑस्ट्रेलियाई डॉलर",
	"AWG":"अरुबान फ्लोरिन",
	"AZN":"अजरबैजानी मांगट",
	"BAM":"बोस्निया-हर्जेगोविना परिवर्तनीय मार्क",
	"BBD":"बारबाडियन डॉलर",
	"BDT":"बांग्लादेशी टका",
	"BGN":"बल्गेरियाई लेव",
	"BHD":"बहरीन दीनार",
	"BIF":"बुरुडियन फ्रैंक",
	"BMD":"बरमूडन डॉलर",
	"BND":"ब्रुनेई डॉलर",
	"BOB":"बोलीविया बोलीवियानो",
	"BRL":"रीयाल",
	"BSD":"बहामियन डॉलर",
	"BTC":"Bitcoin",
	"BTN":"भूटानी Ngultrum",
	"BWP":"बोत्सवाना पुलिया",
	"BYN":"बेलारूसी रूबल",
	"BZD":"बेलीज डॉलर",
	"CAD":"कनाडाई डॉलर",
	"CDF":"कांगो फ्रैंक",
	"CHF":"स्विस फ्रैंक",
	"CLF":"चिली यूनिट ऑफ अकाउंट (यूएफ)",
	"CLP":"चिली पेसो",
	"CNY":"चीनी युआन",
	"COP":"कोलंबिया पेसो",
	"CRC":"कोस्टा रिको कोलोन",
	"CUC":"क्यूबा परिवर्तनीय पेसो",
	"CUP":"क्यूबा पेसो",
	"CVE":"केप वर्डियन एस्कुडो",
	"CZK":"चेक गणराज्य कोरुना",
	"DJF":"जिबूती फ्रैंक",
	"DKK":"दानिश क्रोन",
	"DOP":"डोमिनिकन पेसो",
	"DZD":"अल्जीरियाई दीनार",
	"EGP":"मिस्र के पाउंड",
	"ERN":"इरिट्रिया नक्फा",
	"ETB":"इथियोपिया के बिरर",
	"EUR":"यूरो",
	"FJD":"फिजियन डॉलर",
	"FKP":"फॉकलैंड आइलैंड्स पाउंड",
	"GBP":"ब्रिटिश पाउंड स्टर्लिंग",
	"GEL":"जॉर्जियाई लारी",
	"GGP":"गर्नसे पाउंड",
	"GHS":"घाना सेडी",
	"GIP":"जिब्राल्टर पाउंड",
	"GMD":"गैम्बियन डालसी",
	"GNF":"गिनी फ्रैंक",
	"GTQ":"ग्वाटेमेले क्वेज़ल",
	"GYD":"गुयानेज़ डॉलर",
	"HKD":"हांगकांग डॉलर",
	"HNL":"होंडुरन लेम्पिरा",
	"HRK":"क्रोएशियाई कुंआ",
	"HTG":"हाईटियन गौड़े",
	"HUF":"हंगरी फोर्ट",
	"IDR":"इंडोनेशियाई रुपिया",
	"ILS":"इजरायल ी न्यू शेक़ल",
	"IMP":"Manx पाउंड",
	"INR":"भारतीय रुपया",
	"IQD":"इराकी दीनार",
	"IRR":"ईरानी रियाल",
	"ISK":"आइसलैंडिक क्रोना",
	"JEP":"जर्सी पाउंड",
	"JMD":"जमैका डॉलर",
	"JOD":"जॉर्डन दीनार",
	"JPY":"जापानी येन",
	"KES":"केन्याई शिलिंग",
	"KGS":"किर्गिस्तानी सोम",
	"KHR":"कंबोडियन रियल",
	"KMF":"कोमोरियन फ्रैंक",
	"KPW":"उत्तर कोरियाई जीता",
	"KRW":"दक्षिण कोरियाई जीता",
	"KWD":"कुवैती दीनार",
	"KYD":"केमैन आइलैंड्स डॉलर",
	"KZT":"कजाकिस्तानी टेंगे",
	"LAK":"लाओटियन किप",
	"LBP":"लेबनान पाउंड",
	"LKR":"श्रीलंकाई रुपया",
	"LRD":"लाइबेरिया डॉलर",
	"LSL":"लेसोथो लोती",
	"LTL":"लिथुआनियाई लिटास",
	"LVL":"लातवियाई लैट्स",
	"LYD":"लीबिया दीनार",
	"MAD":"मोरक्को दिरहम",
	"MDL":"मोलदोवन लीउ",
	"MGA":"मलागासी एरिरी",
	"MKD":"मकदूनियाई डेनार",
	"MMK":"म्यानमा क्यात",
	"MNT":"मंगोलियाई तुग्रिक",
	"MOP":"मैकेनीस पटका",
	"MRO":"मॉरितानियान आउगुइया",
	"MUR":"मॉरीशस रुपया",
	"MVR":"मालदीव रुफिया",
	"MWK":"मलावियान क्वाचा",
	"MXN":"मैक्सिकन पेसो",
	"MYR":"मलेशियाई रिंगगिट",
	"MZN":"मोजांबिक मेटिकल",
	"NAD":"नामीबिया डॉलर",
	"NGN":"नाइजीरियाई नायरा",
	"NIO":"निकारागुआ कोर्डोबा",
	"NOK":"नार्वे क्रोन",
	"NPR":"नेपाली रुपया",
	"NZD":"न्यूजीलैंड डॉलर",
	"OMR":"ओमानी रियाल",
	"PAB":"पनामा बाल्बोआ",
	"PEN":"पेरू नुएवो सोल",
	"PGK":"पापुआ न्यू गिनी किना",
	"PHP":"फिलीपीन पेसो",
	"PKR":"पाकिस्तानी रुपया",
	"PLN":"पोलिश ज़लोटी",
	"PYG":"पराग्यूयन ग्वारानी",
	"QAR":"कतरी रियाल",
	"RON":"रोमानियाई लीउ",
	"RSD":"सर्बियाई दीनार",
	"RUB":"रूसी रूबल",
	"RWF":"रवांडा फ्रैंक",
	"SAR":"सऊदी रियाल",
	"SBD":"सोलोमन आइलैंड्स डॉलर",
	"SCR":"सेचेलोइस रुपया",
	"SDG":"सूडानी पाउंड",
	"SEK":"स्वीडिश क्रोना",
	"SGD":"सिंगापुर डॉलर",
	"SHP":"सेंट हेलेना पाउंड",
	"SLL":"सिएरा लियोनियन लियोन",
	"SOS":"सोमाली शिलिंग",
	"SRD":"सूरीनामी डॉलर",
	"STD":"साओ टोमे और प्रिंसिप डोबरा",
	"SVC":"साल्वाडोरन कोलोन",
	"SYP":"सीरियाई पाउंड",
	"SZL":"स्वाजी लिलांगेनी",
	"THB":"थाई बात",
	"TJS":"ताजिकिस्तानी सोमनी",
	"TMT":"तुर्कमेनिस्तानी मांगट",
	"TND":"ट्यूनीशियाई दीनार",
	"TOP":"टोंगन पंगा",
	"TRY":"तुर्की लीरा",
	"TTD":"त्रिनिदाद और टोबैगो डॉलर",
	"TWD":"नई ताइवान डॉलर",
	"TZS":"तंजानिया शिलिंग",
	"UAH":"यूक्रेनी Hryvnia",
	"UGX":"युगांडा शिलिंग",
	"USD":"यूनाइटेड स्टेट्स डॉलर",
	"UYU":"उरुग्वेयन पेसो",
	"UZS":"उज्बेकिस्तान सोम",
	"VES":"वेनेजुएला के बोलिवर फ्यूएर्ते",
	"VND":"वियतनामी दांग",
	"VUV":"वानुअतु वातु",
	"WST":"समोआन ताला",
	"XAF":"सीएफए फ्रैंक बीएसी",
	"XAG":"चांदी (ट्रॉय औंस)",
	"XAU":"सोना (ट्रॉय औंस)",
	"XCD":"ईस्ट कैरेबियन डॉलर",
	"XDR":"विशेष आहरण अधिकार",
	"XOF":"सीएफए फ्रैंक बीसीएओ",
	"XPF":"सीएफपी फ्रैंक",
	"YER":"येमेनी रियाल",
	"ZAR":"दक्षिण अफ्रीकी रैंड",
	"ZMK":"जाम्बिया क्वाचा (पूर्व 2013)",
	"ZMW":"जाम्बिया क्वाचा",
	"ZWL":"जिम्बाब्वे डॉलर",
}
