{
	"line_chart":"nan",
	"app_name":"Prevodník mien",
	"first_fragment_label":"Prvý fragment",
	"second_fragment_label":"Druhý fragment",
	"next":"Ďalšie",
	"previous":"Predchádzajúce",
	"search":"Vyhľadávanie",
	"copied_to_clipboard":"Skopírované do schránky",
	"hello_first_fragment":"Ahoj prvý fragment",
	"hello_second_fragment":"Ahoj druhý fragment. Arg:% 1 $ s",
	"cpv_default_title":"Vyberte farbu",
	"cpv_presets":"Predvoľby",
	"cpv_custom":"Vyberte vlastnú farbu",
	"cpv_select":"Vyberte",
	"cpv_transparency":"Transparentnosť",
	"widget_transparency":"Transparentnosť miniaplikácií",
	"rate_the_app":"Ohodnoťte našu aplikáciu!",
	"rate_app_desc":"Ohodnoťte klepnutím na hviezdičky a „Otvoriť v obchode Google Play“",
	"not_now":"TERAZ NIE",
	"updated_date":"Aktualizované:",
	"monetary_format":"Peňažný formát",
	"decimal_format":"Desatinný formát",
	"don_t_show":"Neukazuj",
	"support":"Pomoc",
	"terms":"Podmienky",
	"privacy_policy":"Ochrana osobných údajov",
	"remove_ads":"Odstrániť reklamu",
	"sub_remove_ads":"Podporte náš projekt malým ročným predplatným",
	"language":"Jazyk",
	"color_selection":"Výber farieb",
	"select_the_gradient":"Vyberte prechod",
	"unlocked":"Odomknuté",
	"locked":"Zamknuté",
	"try_this_color":"Vyskúšajte túto farbu",
	"sub_try_this_color":"Skúste to pred odomknutím",
	"unlock":"Odomknúť",
	"sub_unlock":"Odomknite túto farbu na {item_price}",
	"theme":"Téma",
	"light":"Svetlá farba",
	"dark":"Tmavá farba",
	"wedget_transparency":"Transparentnosť miniaplikácií",
	"by_currency_wiki":"Autor: Currency.wiki",
	"visual_size":"Vizuálna veľkosť",
	"small":"Malý",
	"medium":"Stredná",
	"large":"Veľký",
	"when_opening_app":"Spúšťač loga aplikácie",
	"display_multi_converter":"Multi-Converter",
	"sub_multi_converter":"V predvolenom nastavení otvorí multi-prevodník. POZNÁMKA: Táto funkcia funguje iba so spúšťačom loga aplikácie.",
	"dislay":"Šou",
	"display_currency_code":"Zobraziť kód meny",
	"display_currency_symbol":"Zobraziť symbol meny",
	"display_currency_flag":"Zobraziť vlajku meny",
	"date_format":"Formát dátumu",
	"click_here":"⇒ Kliknite sem",
	"learn_how_to_nadd_widget":"Naučte sa, ako pridať widget",
	"selected":"VYBRANÝ",
	"currency_list":"ZOZNAM MENY",
	"title_add_currency":"PRIDAJ MENU",
	"title_configure":"KONFIGURÁCIA",
	"add_widget":"Pridať miniaplikáciu",
	"convert_widget_single":"Premeniť - slobodný",
	"convert_widget_list":"Prevod - Zoznam",
	"title_select_base_currency":"Vyberte základnú menu",
	"amount":"Množstvo",
	"error_amount_empty":"Zadajte správne sumu",
	"internet_error":"Pripojte sa k internetu",
	"facebook_app_id":"248045086948204",
	"fb_login_protocol_scheme":"fb248045086948204",
	"tab_text_1":"Tab 1",
	"tab_text_2":"Tab 2",
	"title_activity_add_currency":"AddCurrencyActivity",
	"monetary_format_1":"1272.56",
	"monetary_format_2":"1.234,94",
	"monetary_format_3":"39 234.56",
	"monetary_format_4":"39 234,56",
	"decimal_format_1":".02",
	"decimal_format_2":".003",
	"decimal_format_3":".0004",
	"decimal_format_4":".00005",
	"decimal_format_5":".000006",
	"date_format_1":"mm/dd/yy",
	"date_format_2":"dd/mm/yy",
	"iso":"slovenský",
	"AED":"Spojené arabské emiráty Dirham",
	"AFN":"Afganský Afganistan",
	"ALL":"Albánsky Lek",
	"AMD":"Arménska dráma",
	"ANG":"Holandský antillský gulden",
	"AOA":"Angolský kwanza",
	"ARS":"Argentínske peso",
	"AUD":"Austrálsky dolár",
	"AWG":"Aruban Florin",
	"AZN":"Azerbajdžanský Manat",
	"BAM":"Premeniteľná značka Bosny a Hercegoviny",
	"BBD":"Barbadiánsky dolár",
	"BDT":"Bangladéšska Taka",
	"BGN":"Bulharský lev",
	"BHD":"Bahrajnský dinár",
	"BIF":"Burundský frank",
	"BMD":"Bermudský dolár",
	"BND":"Brunejský dolár",
	"BOB":"Bolivian Boliviano",
	"BRL":"Brazílsky real",
	"BSD":"Bahamský dolár",
	"BTC":"Bitcoin",
	"BTN":"Bhutánsky ngultrum",
	"BWP":"Botswanan Pula",
	"BYN":"Bieloruský rubeľ",
	"BZD":"Belize Dollar",
	"CAD":"Kanadský dolár",
	"CDF":"Konžský frank",
	"CHF":"Švajčiarsky frank",
	"CLF":"Čílska účtovná jednotka (UF)",
	"CLP":"Čílske peso",
	"CNY":"Čínsky juan",
	"COP":"Kolumbijské peso",
	"CRC":"Kostarický Colón",
	"CUC":"Kubánske konvertibilné peso",
	"CUP":"Kubánske peso",
	"CVE":"Cape Verdean Escudo",
	"CZK":"Česká republika Koruna",
	"DJF":"Džibutský frank",
	"DKK":"Dánsky Krone",
	"DOP":"Dominikánske peso",
	"DZD":"Alžírsky dinár",
	"EGP":"Egyptská libra",
	"ERN":"Eritrean Nakfa",
	"ETB":"Etiópsky Birr",
	"EUR":"euro",
	"FJD":"Fidžijský dolár",
	"FKP":"Libra Falklandských ostrovov",
	"GBP":"Britská libra šterlingov",
	"GEL":"Gruzínsky Lari",
	"GGP":"Guernsey Libra",
	"GHS":"Ghanaian Cedi",
	"GIP":"Libra Gibraltár",
	"GMD":"Gambie Dalasi",
	"GNF":"Guinejský frank",
	"GTQ":"Guatemalský Quetzal",
	"GYD":"Guyanský dolár",
	"HKD":"Hongkonský dolár",
	"HNL":"Honduran Lempira",
	"HRK":"Chorvátska kuna",
	"HTG":"Haitian Gourde",
	"HUF":"Maďarský forint",
	"IDR":"Indonézska rupia",
	"ILS":"Izraelský nový šekel",
	"IMP":"Manx libra",
	"INR":"Indická rupia",
	"IQD":"Iracký dinár",
	"IRR":"Iránsky rial",
	"ISK":"Islandská Króna",
	"JEP":"Jersey Libra",
	"JMD":"Jamajský dolár",
	"JOD":"Jordánsky dinár",
	"JPY":"Japonský jen",
	"KES":"Keňský šiling",
	"KGS":"Kyrgystani Som",
	"KHR":"Kambodžský Riel",
	"KMF":"Komorský frank",
	"KPW":"Severokórejský won",
	"KRW":"Južná Kórea vyhral",
	"KWD":"Kuvajtský dinár",
	"KYD":"Dolár na Kajmanských ostrovoch",
	"KZT":"Kazachstanský tenge",
	"LAK":"Laotian Kip",
	"LBP":"Libanonská libra",
	"LKR":"Srílanská rupia",
	"LRD":"Libérijský dolár",
	"LSL":"Lesotho Loti",
	"LTL":"Litovský litas",
	"LVL":"Lotyšský lats",
	"LYD":"Líbyjský dinár",
	"MAD":"Marocký Dirham",
	"MDL":"Moldovan Leu",
	"MGA":"Madagaskarská ariary",
	"MKD":"Macedónsky denár",
	"MMK":"Myanma Kyat",
	"MNT":"Mongolský Tugrik",
	"MOP":"Macanese Pataca",
	"MRO":"Mauritánska Ouguiya",
	"MUR":"Maurícijská rupia",
	"MVR":"Maldivian Rufiyaa",
	"MWK":"Malawian Kwacha",
	"MXN":"Mexické peso",
	"MYR":"Malajzijský ringgit",
	"MZN":"Mozambický metrický",
	"NAD":"Namíbijský dolár",
	"NGN":"Nigérijská Naira",
	"NIO":"Nikaragujský Córdoba",
	"NOK":"Nórska Krone",
	"NPR":"Nepálska rupia",
	"NZD":"Novozélandský dolár",
	"OMR":"Ománsky rial",
	"PAB":"Panamský Balboa",
	"PEN":"Peruánsky Nuevo Sol",
	"PGK":"Papua-Nová Guinea Kina",
	"PHP":"Filipínske peso",
	"PKR":"Pakistanská rupia",
	"PLN":"Poľský zlotý",
	"PYG":"Paraguayan Guarani",
	"QAR":"Katarský rial",
	"RON":"Rumunský Leu",
	"RSD":"Srbský dinár",
	"RUB":"Ruský rubeľ",
	"RWF":"Rwandan Franc",
	"SAR":"Saudská Riyal",
	"SBD":"Dolár Šalamúnových ostrovov",
	"SCR":"Seychelóza rupia",
	"SDG":"Sudánska libra",
	"SEK":"Švédska koruna",
	"SGD":"Singapurský dolár",
	"SHP":"Libra sv. Heleny",
	"SLL":"Sierra Leonean Leone",
	"SOS":"Somálsky šiling",
	"SRD":"Surinamský dolár",
	"STD":"Svätý Tomáš a Princov ostrov Dobra",
	"SVC":"Salvadoran Colón",
	"SYP":"Sýrska libra",
	"SZL":"Swazi Lilangeni",
	"THB":"Thai Baht",
	"TJS":"Tajikistani Somoni",
	"TMT":"Turkmenistani Manat",
	"TND":"Tuniský dinár",
	"TOP":"Tongan Paʻanga",
	"TRY":"Turecká líra",
	"TTD":"Trinidad a Tobago dolár",
	"TWD":"Nový taiwanský dolár",
	"TZS":"Tanzánsky šiling",
	"UAH":"Ukrajinská hrivna",
	"UGX":"Ugandský šiling",
	"USD":"Americký dolár",
	"UYU":"Uruguajské peso",
	"UZS":"Uzbekistan Som",
	"VES":"Venezuelský Bolívar Fuerte",
	"VND":"Vietnamský Dong",
	"VUV":"Vanuatu Vatu",
	"WST":"Samoan Tala",
	"XAF":"CFA Franc BEAC",
	"XAG":"Striebro (trójska unca)",
	"XAU":"Zlato (trójska unca)",
	"XCD":"Východokaribský dolár",
	"XDR":"Osobitné práva čerpania",
	"XOF":"CFA Franc BCEAO",
	"XPF":"CFP Franc",
	"YER":"Jemenský rial",
	"ZAR":"Juhoafrický rand",
	"ZMK":"Zambian Kwacha (pred rokom 2013)",
	"ZMW":"Zambie Kwacha",
	"ZWL":"Zimbabwský dolár",
}
