{
    "update": "Opdateret",
    "addCurrency": "Tilføj valuta",
    "selectedCurrency": "Valgt valuta",
    "monetary": "Monetært format",
    "decimal": "Decimalformat",
    "firstTextRatingPage": "Bedøm app'en,",
    "secondTextRatingPage": "Tryk på stjerner, og åbn med Google Play Butik for at vurdere",
    "buttonTextRatingPage": "IKKE NU",
    "removeAds": "Fjern annoncer",
    "removeAdsContent": "Støt vores projekt med et lille årligt abonnement",
    "selectLanguage": "Vælg sprog",
    "english": "dansk",
    "colorsSelection": "Valg af farve",
    "theme": "Tema",
    "light": "Light",
    "dark": "Dark",
    "widgetTransparency": "Widget -gennemsigtighed",
    "visualSize": "Visuel størrelse",
    "A": "A",
    "appLogoLauncher": "App Logo Launcher",
    "multiConverter": "Multi-Converter",
    "multiConverterContent1": "Åbner multi-converter som standard.",
    "multiConverterContent2": "BEMÆRK:",
    "multiConverterContent3": "Denne funktion fungerer kun med applogostarter",
    "display": "Display",
    "display1": "Vis valutakode",
    "display2": "Vis valutasymbol",
    "display3": "Displayvaluta flag",
    "dateFormat": "Dataformat"
  
  }
  
  